parestlib/__init__.py
parestlib/binnts.py
parestlib/problem_suite.py
parestlib/shell_step.py
parestlib/sim_suite.py
parestlib/stochastic_descent.py
parestlib/utils.py
parestlib/version.py
parestlib-0.4.0.dist-info/LICENSE
parestlib-0.4.0.dist-info/METADATA
parestlib-0.4.0.dist-info/WHEEL
parestlib-0.4.0.dist-info/top_level.txt
parestlib-0.4.0.dist-info/RECORD
