Metadata-Version: 2.1
Name: parestlib
Version: 0.4.0
Summary: Parameter estimation library
Home-page: http://covasim.org
Author: Cliff Kerr, Daniel Klein
Author-email: covasim@idmod.org
License: UNKNOWN
Keywords: parameter,estimation,posterior,sampling,stochastic,optimization
Platform: OS Independent
Classifier: Environment :: Console
Classifier: Intended Audience :: Science/Research
Classifier: License :: Other/Proprietary License
Classifier: Operating System :: OS Independent
Classifier: Programming Language :: Python
Classifier: Topic :: Software Development :: Libraries :: Python Modules
Classifier: Development Status :: 4 - Beta
Classifier: Programming Language :: Python :: 3.7
Requires-Dist: matplotlib (>=2.2.2)
Requires-Dist: numpy (>=1.10.1)
Requires-Dist: scipy (>=1.2.0)
Requires-Dist: sciris (>=0.15.6)
Requires-Dist: statsmodels
